MANIFEST.in
README.txt
setup.cfg
setup.py
docs/HISTORY.txt
docs/LICENSE.GPL
docs/LICENSE.txt
redomino/__init__.py
redomino/__init__.pyc
redomino.tinymceplugins.snippet.egg-info/PKG-INFO
redomino.tinymceplugins.snippet.egg-info/SOURCES.txt
redomino.tinymceplugins.snippet.egg-info/dependency_links.txt
redomino.tinymceplugins.snippet.egg-info/entry_points.txt
redomino.tinymceplugins.snippet.egg-info/namespace_packages.txt
redomino.tinymceplugins.snippet.egg-info/not-zip-safe
redomino.tinymceplugins.snippet.egg-info/requires.txt
redomino.tinymceplugins.snippet.egg-info/top_level.txt
redomino/tinymceplugins/__init__.py
redomino/tinymceplugins/__init__.pyc
redomino/tinymceplugins/snippet/__init__.py
redomino/tinymceplugins/snippet/configure.zcml
redomino/tinymceplugins/snippet/setuphandlers.py
redomino/tinymceplugins/snippet/tests.py
redomino/tinymceplugins/snippet/locales/en/LC_MESSAGES/tinymce.snippet.mo
redomino/tinymceplugins/snippet/locales/en/LC_MESSAGES/tinymce.snippet.po
redomino/tinymceplugins/snippet/locales/it/LC_MESSAGES/tinymce.snippet.mo
redomino/tinymceplugins/snippet/locales/it/LC_MESSAGES/tinymce.snippet.po
redomino/tinymceplugins/snippet/profiles/default/metadata.xml
redomino/tinymceplugins/snippet/profiles/default/redomino.tinymceplugins.snippet.txt
redomino/tinymceplugins/snippet/profiles/default/redomino.tinymceplugins.snippet_various.txt
redomino/tinymceplugins/snippet/profiles/default/skins.xml
redomino/tinymceplugins/snippet/profiles/default/tinymce.xml
redomino/tinymceplugins/snippet/skins/tinymce_plugin_snippet/snippet/dialog.htm.pt
redomino/tinymceplugins/snippet/skins/tinymce_plugin_snippet/snippet/editor_plugin.js
redomino/tinymceplugins/snippet/skins/tinymce_plugin_snippet/snippet/css/dialog.css.dtml
redomino/tinymceplugins/snippet/skins/tinymce_plugin_snippet/snippet/img/snippet.gif
redomino/tinymceplugins/snippet/skins/tinymce_plugin_snippet/snippet/js/dialog.js
redomino/tinymceplugins/snippet/skins/tinymce_plugin_snippet/snippet/langs/ar.js
redomino/tinymceplugins/snippet/skins/tinymce_plugin_snippet/snippet/langs/ar_dlg.js
redomino/tinymceplugins/snippet/skins/tinymce_plugin_snippet/snippet/langs/az.js
redomino/tinymceplugins/snippet/skins/tinymce_plugin_snippet/snippet/langs/az_dlg.js
redomino/tinymceplugins/snippet/skins/tinymce_plugin_snippet/snippet/langs/be.js
redomino/tinymceplugins/snippet/skins/tinymce_plugin_snippet/snippet/langs/be_dlg.js
