Metadata-Version: 1.0
Name: redomino.tinymceplugins.snippet
Version: 0.0.4
Summary: A TinyMCE plugin for pasting snippets inside a text
Home-page: https://github.com/redomino/redomino.tinymceplugins.snippet
Author: Maurizio Lupo
Author-email: maurizio.lupo@redomino.com
License: GPL
Keywords: plone tinymce plugin
Platform: UNKNOWN
Classifier: Framework :: Plone
Classifier: Programming Language :: Python
Classifier: Programming Language :: JavaScript
